karnaf_tools/__init__.py
karnaf_tools/utils.py
karnaf_tools-0.0.6.dist-info/LICENSE
karnaf_tools-0.0.6.dist-info/METADATA
karnaf_tools-0.0.6.dist-info/WHEEL
karnaf_tools-0.0.6.dist-info/top_level.txt
karnaf_tools-0.0.6.dist-info/RECORD
